{
  "wardCode": "34209",
  "wardName": "三次市",
  "towns": [
    {
      "name": "三原町",
      "chome": []
    },
    {
      "name": "三和町上壱",
      "chome": []
    },
    {
      "name": "三和町上板木",
      "chome": []
    },
    {
      "name": "三和町下板木",
      "chome": []
    },
    {
      "name": "三和町大力谷",
      "chome": []
    },
    {
      "name": "三和町敷名",
      "chome": []
    },
    {
      "name": "三和町有原",
      "chome": []
    },
    {
      "name": "三和町福田",
      "chome": []
    },
    {
      "name": "三和町羽出庭",
      "chome": []
    },
    {
      "name": "三和町飯田",
      "chome": []
    },
    {
      "name": "三次町",
      "chome": []
    },
    {
      "name": "三良坂町三良坂",
      "chome": []
    },
    {
      "name": "三良坂町仁賀",
      "chome": []
    },
    {
      "name": "三良坂町光清",
      "chome": []
    },
    {
      "name": "三良坂町大谷",
      "chome": []
    },
    {
      "name": "三良坂町岡田",
      "chome": []
    },
    {
      "name": "三良坂町棗原",
      "chome": []
    },
    {
      "name": "三良坂町灰塚",
      "chome": []
    },
    {
      "name": "三良坂町田利",
      "chome": []
    },
    {
      "name": "三良坂町皆瀬",
      "chome": []
    },
    {
      "name": "三良坂町長田",
      "chome": []
    },
    {
      "name": "三若町",
      "chome": []
    },
    {
      "name": "上川立町",
      "chome": []
    },
    {
      "name": "上志和地町",
      "chome": []
    },
    {
      "name": "上田町",
      "chome": []
    },
    {
      "name": "下川立町",
      "chome": []
    },
    {
      "name": "下志和地町",
      "chome": []
    },
    {
      "name": "作木町上作木",
      "chome": []
    },
    {
      "name": "作木町下作木",
      "chome": []
    },
    {
      "name": "作木町伊賀和志",
      "chome": []
    },
    {
      "name": "作木町光守",
      "chome": []
    },
    {
      "name": "作木町大山",
      "chome": []
    },
    {
      "name": "作木町大津",
      "chome": []
    },
    {
      "name": "作木町大畠",
      "chome": []
    },
    {
      "name": "作木町岡三渕",
      "chome": []
    },
    {
      "name": "作木町森山中",
      "chome": []
    },
    {
      "name": "作木町森山東",
      "chome": []
    },
    {
      "name": "作木町森山西",
      "chome": []
    },
    {
      "name": "作木町西野",
      "chome": []
    },
    {
      "name": "作木町門田",
      "chome": []
    },
    {
      "name": "作木町香淀",
      "chome": []
    },
    {
      "name": "十日市中",
      "chome": [
        "一丁目",
        "三丁目",
        "二丁目",
        "四丁目"
      ]
    },
    {
      "name": "十日市南",
      "chome": [
        "一丁目",
        "七丁目",
        "三丁目",
        "二丁目",
        "五丁目",
        "六丁目",
        "四丁目"
      ]
    },
    {
      "name": "十日市東",
      "chome": [
        "一丁目",
        "三丁目",
        "二丁目",
        "五丁目",
        "六丁目",
        "四丁目"
      ]
    },
    {
      "name": "十日市町",
      "chome": []
    },
    {
      "name": "十日市西",
      "chome": [
        "一丁目",
        "三丁目",
        "二丁目",
        "五丁目",
        "六丁目",
        "四丁目"
      ]
    },
    {
      "name": "南畑敷町",
      "chome": []
    },
    {
      "name": "吉舎町三玉",
      "chome": []
    },
    {
      "name": "吉舎町上安田",
      "chome": []
    },
    {
      "name": "吉舎町丸田",
      "chome": []
    },
    {
      "name": "吉舎町吉舎",
      "chome": []
    },
    {
      "name": "吉舎町吉舎川之内",
      "chome": []
    },
    {
      "name": "吉舎町安田",
      "chome": []
    },
    {
      "name": "吉舎町徳市",
      "chome": []
    },
    {
      "name": "吉舎町敷地",
      "chome": []
    },
    {
      "name": "吉舎町桧",
      "chome": []
    },
    {
      "name": "吉舎町海田原",
      "chome": []
    },
    {
      "name": "吉舎町清綱",
      "chome": []
    },
    {
      "name": "吉舎町矢井",
      "chome": []
    },
    {
      "name": "吉舎町矢野地",
      "chome": []
    },
    {
      "name": "吉舎町知和",
      "chome": []
    },
    {
      "name": "吉舎町辻",
      "chome": []
    },
    {
      "name": "吉舎町雲通",
      "chome": []
    },
    {
      "name": "向江田町",
      "chome": []
    },
    {
      "name": "君田町東入君",
      "chome": []
    },
    {
      "name": "君田町櫃田",
      "chome": []
    },
    {
      "name": "君田町泉吉田",
      "chome": []
    },
    {
      "name": "君田町石原",
      "chome": []
    },
    {
      "name": "君田町茂田",
      "chome": []
    },
    {
      "name": "君田町藤兼",
      "chome": []
    },
    {
      "name": "君田町西入君",
      "chome": []
    },
    {
      "name": "和知町",
      "chome": []
    },
    {
      "name": "四拾貫町",
      "chome": []
    },
    {
      "name": "塩町",
      "chome": []
    },
    {
      "name": "大田幸町",
      "chome": []
    },
    {
      "name": "小文町",
      "chome": []
    },
    {
      "name": "小田幸町",
      "chome": []
    },
    {
      "name": "山家町",
      "chome": []
    },
    {
      "name": "布野町上布野",
      "chome": []
    },
    {
      "name": "布野町下布野",
      "chome": []
    },
    {
      "name": "布野町戸河内",
      "chome": []
    },
    {
      "name": "布野町横谷",
      "chome": []
    },
    {
      "name": "廻神町",
      "chome": []
    },
    {
      "name": "後山町",
      "chome": []
    },
    {
      "name": "志幸町",
      "chome": []
    },
    {
      "name": "日下町",
      "chome": []
    },
    {
      "name": "有原町",
      "chome": []
    },
    {
      "name": "木乗町",
      "chome": []
    },
    {
      "name": "東河内町",
      "chome": []
    },
    {
      "name": "東酒屋町",
      "chome": []
    },
    {
      "name": "江田川之内町",
      "chome": []
    },
    {
      "name": "海渡町",
      "chome": []
    },
    {
      "name": "甲奴町太郎丸",
      "chome": []
    },
    {
      "name": "甲奴町宇賀",
      "chome": []
    },
    {
      "name": "甲奴町小童",
      "chome": []
    },
    {
      "name": "甲奴町抜湯",
      "chome": []
    },
    {
      "name": "甲奴町有田",
      "chome": []
    },
    {
      "name": "甲奴町本郷",
      "chome": []
    },
    {
      "name": "甲奴町梶田",
      "chome": []
    },
    {
      "name": "甲奴町福田",
      "chome": []
    },
    {
      "name": "甲奴町西野",
      "chome": []
    },
    {
      "name": "畠敷町",
      "chome": []
    },
    {
      "name": "石原町",
      "chome": []
    },
    {
      "name": "秋町",
      "chome": []
    },
    {
      "name": "穴笠町",
      "chome": []
    },
    {
      "name": "粟屋町",
      "chome": []
    },
    {
      "name": "糸井町",
      "chome": []
    },
    {
      "name": "西河内町",
      "chome": []
    },
    {
      "name": "西酒屋町",
      "chome": []
    },
    {
      "name": "青河町",
      "chome": []
    },
    {
      "name": "高杉町",
      "chome": []
    }
  ]
}